zclip/__init__.py
zclip/zclip.py
zclip/zclip_lightning_callback.py
zclip-1.0.0.dist-info/METADATA
zclip-1.0.0.dist-info/WHEEL
zclip-1.0.0.dist-info/licenses/LICENSE
zclip-1.0.0.dist-info/RECORD
