Metadata-Version: 2.4
Name: zclip
Version: 1.0.0
Summary: ZClip: Adaptive Spike Mitigation for LLM Pre-Training
Project-URL: Homepage, https://pypi.org/project/zclip/
Project-URL: Repository, https://github.com/bluorion-com/ZClip
Author: BluOrion
License:                                  Apache License
License-File: LICENSE
Keywords: artificial intelligence
Classifier: Development Status :: 4 - Beta
Classifier: Intended Audience :: Developers
Classifier: License :: OSI Approved :: MIT License
Classifier: Programming Language :: Python :: 3.10
Classifier: Topic :: Scientific/Engineering :: Artificial Intelligence
Requires-Python: >=3.10
Requires-Dist: torch>=2.0.0
Provides-Extra: dev
Requires-Dist: black; extra == 'dev'
Requires-Dist: flake8; extra == 'dev'
Requires-Dist: mypy; extra == 'dev'
Requires-Dist: pytest; extra == 'dev'
Requires-Dist: pytest-cov; extra == 'dev'
Requires-Dist: pytest-shard; extra == 'dev'
Provides-Extra: examples
Provides-Extra: lightning
Requires-Dist: lightning>=2.0.0; extra == 'lightning'
Provides-Extra: test
Requires-Dist: pytest; extra == 'test'
Requires-Dist: pytest-cov; extra == 'test'
Requires-Dist: pytest-shard; extra == 'test'
Provides-Extra: test-lightning
Requires-Dist: lightning>=2.0.0; extra == 'test-lightning'
Requires-Dist: pytest; extra == 'test-lightning'
Requires-Dist: pytest-cov; extra == 'test-lightning'
Requires-Dist: pytest-shard; extra == 'test-lightning'
